LICENSE
MANIFEST.in
README.md
setup.py
lanstudio/__init__.py
lanstudio/cli.py
lanstudio/debug.py
lanstudio/event_stream.py
lanstudio/job_settings.py
lanstudio.egg-info/PKG-INFO
lanstudio.egg-info/SOURCES.txt
lanstudio.egg-info/dependency_links.txt
lanstudio.egg-info/entry_points.txt
lanstudio.egg-info/requires.txt
lanstudio.egg-info/top_level.txt
lanstudio/app/__init__.py
lanstudio/app/api.py
lanstudio/app/config.py
lanstudio/app/mixin.py
lanstudio/app/swagger.py
lanstudio/app/blueprints/__init__.py
lanstudio/app/blueprints/assets/__init__.py
lanstudio/app/blueprints/assets/resources.py
lanstudio/app/blueprints/auth/__init__.py
lanstudio/app/blueprints/auth/resources.py
lanstudio/app/blueprints/breakdown/__init__.py
lanstudio/app/blueprints/breakdown/resources.py
lanstudio/app/blueprints/comments/__init__.py
lanstudio/app/blueprints/comments/resources.py
lanstudio/app/blueprints/crud/__init__.py
lanstudio/app/blueprints/crud/asset_instance.py
lanstudio/app/blueprints/crud/attachment_file.py
lanstudio/app/blueprints/crud/base.py
lanstudio/app/blueprints/crud/comments.py
lanstudio/app/blueprints/crud/custom_action.py
lanstudio/app/blueprints/crud/day_off.py
lanstudio/app/blueprints/crud/department.py
lanstudio/app/blueprints/crud/entity.py
lanstudio/app/blueprints/crud/entity_link.py
lanstudio/app/blueprints/crud/entity_type.py
lanstudio/app/blueprints/crud/event.py
lanstudio/app/blueprints/crud/file_status.py
lanstudio/app/blueprints/crud/metadata_descriptor.py
lanstudio/app/blueprints/crud/milestone.py
lanstudio/app/blueprints/crud/news.py
lanstudio/app/blueprints/crud/notification.py
lanstudio/app/blueprints/crud/organisation.py
lanstudio/app/blueprints/crud/output_file.py
lanstudio/app/blueprints/crud/output_type.py
lanstudio/app/blueprints/crud/person.py
lanstudio/app/blueprints/crud/playlist.py
lanstudio/app/blueprints/crud/preview_background_file.py
lanstudio/app/blueprints/crud/preview_file.py
lanstudio/app/blueprints/crud/project.py
lanstudio/app/blueprints/crud/project_status.py
lanstudio/app/blueprints/crud/schedule_item.py
lanstudio/app/blueprints/crud/search_filter.py
lanstudio/app/blueprints/crud/search_filter_group.py
